Metadata-Version: 2.1
Name: DescomplicandoACria-oDePacotes
Version: 0.0.1
Summary: DIO project
Home-page: https://github.com/ANACAPELETTI/DescomplicandoACriaçãoDePacotes
Author: Ana Capeletti
Author-email: anaalm@alunos.utfpr.edu.br
Requires-Python: >=3.8
Requires-Dist: matplotlib
Requires-Dist: numpy
Requires-Dist: scikit-image (>=0.16.1)
